{
  "AppAssociations": [
    {
      "Id": "515f38f4-2ed4-48e6-9b5e-dd229a0d17d0",
      "AppPath": "",
      "AppName": "\u666E\u901A\u5F85\u529E",
      "IsInjected": false,
      "IsNonApp": true,
      "TodoItems": [
        {
          "Id": "80a0865e-ca95-447b-ac7e-67706557119c",
          "ParentId": "",
          "Content": "\u666E\u901A\u5F85\u529E\u98791",
          "IsCompleted": false,
          "IsExpanded": false,
          "SubItems": [],
          "Description": ""
        },
        {
          "Id": "0da33de7-bfc6-499d-b5f7-d79c14284967",
          "ParentId": "",
          "Content": "\u666E\u901A\u5F85\u529E\u98792",
          "IsCompleted": false,
          "IsExpanded": false,
          "SubItems": [],
          "Description": ""
        }
      ],
      "IsExpanded": false,
      "Description": ""
    },
    {
      "Id": "0d8aa42f-54e6-4742-9012-02d636809fa0",
      "AppPath": "C:\\WINDOWS\\system32\\notepad.exe",
      "AppName": "\u8BB0\u4E8B\u672C",
      "IsInjected": true,
      "IsNonApp": false,
      "TodoItems": [
        {
          "Id": "1288492e-2d0a-47f6-a92c-39baa235c80c",
          "ParentId": "",
          "Content": "\u8F6F\u4EF6\u5F85\u529E\u98791",
          "IsCompleted": false,
          "IsExpanded": false,
          "SubItems": [],
          "Description": ""
        },
        {
          "Id": "7530d3de-9e57-42c7-8e0c-cbfae479de80",
          "ParentId": "",
          "Content": "\u8F6F\u4EF6\u5F85\u529E\u98792",
          "IsCompleted": false,
          "IsExpanded": false,
          "SubItems": [],
          "Description": ""
        }
      ],
      "IsExpanded": false,
      "Description": ""
    }
  ],
  "ThemeType": "Default",
  "ThemeColor": "#2196F3",
  "OverlayBackground": "#D3D3D3",
  "OverlayOpacity": 0.3
}